scrapy_distributed/__init__.py
scrapy_distributed/amqp_utils/__init__.py
scrapy_distributed/amqp_utils/connection.py
scrapy_distributed/amqp_utils/defaults.py
scrapy_distributed/common/__init__.py
scrapy_distributed/common/queue_config.py
scrapy_distributed/dupefilters/__init__.py
scrapy_distributed/dupefilters/redis_bloom.py
scrapy_distributed/middlewares/__init__.py
scrapy_distributed/middlewares/amqp.py
scrapy_distributed/middlewares/common.py
scrapy_distributed/middlewares/kafka.py
scrapy_distributed/pipelines/__init__.py
scrapy_distributed/pipelines/amqp.py
scrapy_distributed/pipelines/kafka.py
scrapy_distributed/queues/__init__.py
scrapy_distributed/queues/amqp.py
scrapy_distributed/queues/common.py
scrapy_distributed/queues/kafka.py
scrapy_distributed/redis_utils/__init__.py
scrapy_distributed/redis_utils/connection.py
scrapy_distributed/redis_utils/defaults.py
scrapy_distributed/schedulers/__init__.py
scrapy_distributed/schedulers/common.py
scrapy_distributed/schedulers/redis_bloom.py
scrapy_distributed/spiders/__init__.py
scrapy_distributed/spiders/redis_bloom.py
scrapy_distributed/spiders/sitemap.py
Scrapy_Distributed-2023.4.23.dist-info/METADATA
Scrapy_Distributed-2023.4.23.dist-info/WHEEL
Scrapy_Distributed-2023.4.23.dist-info/top_level.txt
Scrapy_Distributed-2023.4.23.dist-info/RECORD
