Metadata-Version: 2.1
Name: Scrapy-Distributed
Version: 2023.4.23
Summary: A series distributed components for Scrapy framework
Home-page: https://github.com/Insutanto/scrapy-distributed
Author: Insutanto
Maintainer: Insutanto
Maintainer-email: insutantow@gmail.com
License: BSD
Project-URL: Documentation, https://github.com/Insutanto/scrapy-distributed
Project-URL: Source, https://github.com/Insutanto/scrapy-distributed
Project-URL: Tracker, https://github.com/Insutanto/scrapy-distributed/issues
Classifier: Development Status :: 4 - Beta
Classifier: Intended Audience :: Developers
Classifier: License :: OSI Approved :: BSD License
Classifier: Operating System :: OS Independent
Classifier: Programming Language :: Python
Classifier: Programming Language :: Python :: 3
Classifier: Programming Language :: Python :: 3.6
Classifier: Programming Language :: Python :: 3.7
Classifier: Programming Language :: Python :: 3.8
Classifier: Programming Language :: Python :: Implementation :: CPython
Classifier: Programming Language :: Python :: Implementation :: PyPy
Classifier: Topic :: Internet :: WWW/HTTP
Classifier: Topic :: Software Development :: Libraries :: Application Frameworks
Classifier: Topic :: Software Development :: Libraries :: Python Modules
Requires-Python: >=3.6
Requires-Dist: scrapy (>=1.8.0)
Requires-Dist: pika (>=1.0.0)
Requires-Dist: redisbloom (>=0.2.0)
Requires-Dist: redis (>=3.0.1)
Requires-Dist: kafka-python (>=1.4.7)
